README.rst
setup.py
meowlogtool/__init__.py
meowlogtool/log_util.py
meowlogtool.egg-info/PKG-INFO
meowlogtool.egg-info/SOURCES.txt
meowlogtool.egg-info/dependency_links.txt
meowlogtool.egg-info/requires.txt
meowlogtool.egg-info/top_level.txt