Metadata-Version: 1.1
Name: meowlogtool
Version: 0.1.5
Summary: A python logger util for cat
Home-page: https://github.com/ttpro1995/MeowLogTool
Author: Thai Thien
Author-email: tthien@apcs.vn
License: MIT
Keywords: logger log
Platform: UNKNOWN
Classifier: Development Status :: 4 - Beta
Classifier: Intended Audience :: Developers
Classifier: Topic :: Software Development
Classifier: License :: OSI Approved :: MIT License
Classifier: Programming Language :: Python :: 2
Classifier: Programming Language :: Python :: 2.7
Classifier: Programming Language :: Python :: 3
Classifier: Programming Language :: Python :: 3.3
Classifier: Programming Language :: Python :: 3.4
Classifier: Programming Language :: Python :: 3.5
